{
  "site_title": "Little Nicky by Nick Robinson",
  "block_list": [
    {
      "title": "Video Tutorial",
      "date": "Jul 14, 2020",
      "caption": {
        "type": "video",
        "videoId": "Gg6B-1MrH4A"
      }
    },
    {
      "title": "More Designs from Nick Robinson",
      "body": "<ul><li><a href=\"./1lp6L-6vpGs.html\">Giraffe by Nick Robinson</a></li><li><a href=\"./Gg6B-1MrH4A.html\">Little Nicky by Nick Robinson</a></li><li><a href=\"./bpCmlCfFoHk.html\">Skunk by Nick Robinson</a></li><li><a href=\"./e9fm86pwLGo.html\">Tri Plane by Nick Robinson</a></li></ul>"
    }
  ]
}