{
  "site_title": "Butterfly by Dokuohtei Nakano",
  "block_list": [
    {
      "title": "Video Tutorial",
      "date": "2020-09-12",
      "body": "<p>Learn how to fold an Origami Decorative Butterfly designed by Dokuohtei Nakano in this video. This tutorial is is 1:42 minute long. Tried to make it less than a minute but the video would have been too fast to follow. \n \nThanks for watching! \nWilson Lee @Heap Art  \n \n<p>",
      "caption": {
        "type": "video",
        "videoId": "u21l107kR1k",
        "beforeBody": true
      }
    },
    {
      "title": "More Designs from Dokuohtei Nakano",
      "body": "<ul><li><a href=\"./u21l107kR1k.html\">Butterfly by Dokuohtei Nakano</a></li></ul>"
    }
  ],
  "meta_description": "Heap Art Origami tutorial, How to fold Butterfly by Dokuohtei Nakano",
  "meta_keywords": "Heap Art Origami Tutorial, Heap Art, origami, tutorial, video, how to, short video, vertical video, butterfly by dokuohtei nakano, Dokuohtei Nakano",
  "background_image": "https://i.ytimg.com/vi/u21l107kR1k/maxresdefault.jpg"
}